faKy/__init__.py
faKy/faKy.py
faKy/en_core_web_md-2.3.1/MANIFEST.in
faKy/en_core_web_md-2.3.1/PKG-INFO
faKy/en_core_web_md-2.3.1/meta.json
faKy/en_core_web_md-2.3.1/setup.cfg
faKy/en_core_web_md-2.3.1/setup.py
faKy/en_core_web_md-2.3.1/en_core_web_md/__init__.py
faKy/en_core_web_md-2.3.1/en_core_web_md/meta.json
faKy-2.1.0.dist-info/METADATA
faKy-2.1.0.dist-info/WHEEL
faKy-2.1.0.dist-info/top_level.txt
faKy-2.1.0.dist-info/RECORD
