Metadata-Version: 2.1
Name: faKy
Version: 2.1.0
Summary: faKy is a Python library for text analysis. It provides functions for readability, complexity, sentiment, and statistical analysis in the scope of fake news detection.
Author: Sandro Barres Hamers
Author-email: sbarreshamers@gmail.com
Requires-Dist: numpy (==1.24.2)
Requires-Dist: pandas (==1.3.4)
Requires-Dist: spacy-readability (==1.4.1)
Requires-Dist: nltk (==3.7)
Requires-Dist: vaderSentiment (==3.3.2)
Provides-Extra: vader
Requires-Dist: vaderSentiment ; extra == 'vader'
